CHANGES.txt
INSTALL.txt
LICENSE.txt
MANIFEST.in
Makefile
README.txt
TODO.txt
build.bat
fi2pxd.py
lcms2pxd.py
license-fi.txt
license-gpl.txt
setup.cfg
setup.py
contrib/benchmark.py
contrib/build.py
contrib/diff.py
docs/Makefile
docs/conf.py
docs/index.rst
docs/make.bat
docs/supported_filetypes.csv
docs/build/html/genindex.html
docs/build/html/index.html
docs/build/html/search.html
docs/build/html/_sources/index.txt
docs/build/html/_static/basic.css
docs/build/html/_static/default.css
docs/build/html/_static/pygments.css
smc.freeimage.egg-info/PKG-INFO
smc.freeimage.egg-info/SOURCES.txt
smc.freeimage.egg-info/dependency_links.txt
smc.freeimage.egg-info/namespace_packages.txt
smc.freeimage.egg-info/not-zip-safe
smc.freeimage.egg-info/top_level.txt
smc/freeimage/__init__.py
smc/freeimage/_freeimage.c
smc/freeimage/_freeimage.pyx
smc/freeimage/_lcms.pxi
smc/freeimage/enums.py
smc/freeimage/ficonstants.c
smc/freeimage/freeimage.pxd
smc/freeimage/lcms.pxd
smc/freeimage/lcmsconstants.c
smc/freeimage/smc_fi.h
smc/freeimage/smc_fi.pxd
smc/freeimage/tests/__init__.py
smc/freeimage/tests/__main__.py
smc/freeimage/tests/benchmark.py
smc/freeimage/tests/common.py
smc/freeimage/tests/memtest.py
smc/freeimage/tests/test_enums.py
smc/freeimage/tests/test_image.py
smc/freeimage/tests/test_lcms.py
smc/freeimage/tests/test_simple.py
smc/freeimage/tests/testdata/1bpp.tiff
smc/freeimage/tests/testdata/README.txt
smc/freeimage/tests/testdata/buffertest.tiff
smc/freeimage/tests/testdata/cmy.icm
smc/freeimage/tests/testdata/cmyk.tiff
smc/freeimage/tests/testdata/lcmslabi.icm
smc/freeimage/tests/testdata/lcmsxyzi.icm
smc/freeimage/tests/testdata/lzw_pon.tiff
smc/freeimage/tests/testdata/monoscnr.icm
smc/freeimage/tests/testdata/multipage.tiff
smc/freeimage/tests/testdata/non_pon_large.tiff
smc/freeimage/tests/testdata/pon.jpg
smc/freeimage/tests/testdata/srgb_color_space_profile.icm
smc/freeimage/tests/testdata/srgbspac.icm
smc/freeimage/tests/testdata/tifflab8spac.icm
smc/freeimage/tests/testdata/tr01_d50.icm
smc/freeimage/tests/testdata/ycc601.icm
smc/freeimage/tests/testdata/ycc709.icm
static/README.txt
windows/FreeImage.h
windows/README.txt
windows/inttypes.h
windows/lcms2.h
windows/unistd.h
